setup.py
genee_puppet/__init__.py
genee_puppet_cli.egg-info/PKG-INFO
genee_puppet_cli.egg-info/SOURCES.txt
genee_puppet_cli.egg-info/dependency_links.txt
genee_puppet_cli.egg-info/entry_points.txt
genee_puppet_cli.egg-info/top_level.txt