Metadata-Version: 1.1
Name: genee-puppet-cli
Version: 0.1.0
Summary: Genee Puppet Tools
Home-page: https://github.com/iamfat/genee-puppet-cli
Author: Jia Huang
Author-email: iamfat@gmail.com
License: MIT
Keywords: genee puppet
Platform: UNKNOWN
Classifier: Development Status :: 3 - Alpha
Classifier: Intended Audience :: Developers
Classifier: Topic :: Utilities
Classifier: License :: OSI Approved :: MIT License
